LICENSE
MANIFEST.in
README.md
README.ru.md
pyproject.toml
setup.cfg
setup.py
src/browserpedals/__init__.py
src/browserpedals/browserpedals.py
src/browserpedals.egg-info/PKG-INFO
src/browserpedals.egg-info/SOURCES.txt
src/browserpedals.egg-info/dependency_links.txt
src/browserpedals.egg-info/requires.txt
src/browserpedals.egg-info/top_level.txt
src/browserpedals/browserauto/__init__.py
src/browserpedals/browserauto/multitab.py
src/browserpedals/browserauto/webdriverex.py
src/browserpedals/browserpedals_options/__init__.py
src/browserpedals/browserpedals_options/browserpedals_options.txt
src/browserpedals/launcher/__init__.py
src/browserpedals/launcher/bin/py.ico
src/browserpedals/launcher/bin/py.launcher
src/browserpedals/pedals/__init__.py
src/browserpedals/pedals/usepedals.py
src/browserpedals/pedals/detect/__init__.py
src/browserpedals/pedals/detect/detectpedals.py
src/browserpedals/pedals/detect/auto_detected_pedals/__init__.py
src/browserpedals/pedals/detect/auto_detected_pedals/auto_detected_pedals.txt
src/browserpedals/pedals/detect/ui/__init__.py
src/browserpedals/pedals/detect/ui/browserui.py
src/browserpedals/pedals/detect/ui/cmdlineui.py
src/browserpedals/pedals/detect/ui/dialog/__init__.py
src/browserpedals/pedals/detect/ui/dialog/js/ui_check_user_input.js
src/browserpedals/pedals/detect/ui/dialog/js/ui_close.js
src/browserpedals/pedals/detect/ui/dialog/js/ui_on_event.js
src/browserpedals/pedals/detect/ui/dialog/js/ui_open.js
src/browserpedals/pedals/detect/ui/dialog/js/ui_setup_buttons.js
src/browserpedals/pedals/detect/ui/dialog/js/ui_show_progress.js
src/browserpedals/pedals/detect/ui/dialog/js/ui_z_index.js
src/browserpedals/pedals/detect/ui/dialog/js/css/ui_open.css
src/browserpedals/pedals/detect/ui/i18n/__init__.py
src/browserpedals/pedals/detect/ui/i18n/browserpedals.pot
src/browserpedals/pedals/detect/ui/i18n/languages.py
src/browserpedals/pedals/detect/ui/i18n/data_dirs/__init__.py
src/browserpedals/pedals/detect/ui/i18n/data_dirs/appdata.py
src/browserpedals/pedals/detect/ui/i18n/language_names/__init__.py
src/browserpedals/pedals/detect/ui/i18n/language_names/language_names.txt
src/browserpedals/pedals/detect/ui/i18n/locale/__init__.py
