Metadata-Version: 2.1
Name: browserpedals
Version: 0.0.7
Summary: Control videos in web browser with pedals
Home-page: https://github.com/shmygov/browserpedals
Author: Dmitry Shmygov
Author-email: shmygov@rambler.ru
License: UNKNOWN
Keywords: browser foot pedals video audio transcribing pause play typing subtitles selenium webdriver
Platform: UNKNOWN
Classifier: Intended Audience :: End Users/Desktop
Classifier: Intended Audience :: Developers
Classifier: License :: OSI Approved :: MIT License
Classifier: Operating System :: Microsoft :: Windows
Classifier: Operating System :: POSIX
Classifier: Programming Language :: Python :: 3
Classifier: Programming Language :: JavaScript
Classifier: Environment :: Web Environment
Classifier: Topic :: Multimedia :: Video :: Display
Classifier: Topic :: Multimedia :: Sound/Audio
Classifier: Topic :: Printing
Classifier: Topic :: Internet
Requires-Python: >=3.6
License-File: LICENSE
